tabcmd/__init__.py
tabcmd/__main__.py
tabcmd/tabcmd.py
tabcmd/version.py
tabcmd/commands/__init__.py
tabcmd/commands/commands.py
tabcmd/commands/constants.py
tabcmd/commands/server.py
tabcmd/commands/auth/__init__.py
tabcmd/commands/auth/login_command.py
tabcmd/commands/auth/logout_command.py
tabcmd/commands/auth/session.py
tabcmd/commands/datasources_and_workbooks/__init__.py
tabcmd/commands/datasources_and_workbooks/datasources_and_workbooks_command.py
tabcmd/commands/datasources_and_workbooks/datasources_workbooks_views_url_parser.py
tabcmd/commands/datasources_and_workbooks/delete_command.py
tabcmd/commands/datasources_and_workbooks/export_command.py
tabcmd/commands/datasources_and_workbooks/get_url_command.py
tabcmd/commands/datasources_and_workbooks/publish_command.py
tabcmd/commands/datasources_and_workbooks/runschedule_command.py
tabcmd/commands/extracts/__init__.py
tabcmd/commands/extracts/create_extracts_command.py
tabcmd/commands/extracts/decrypt_extracts_command.py
tabcmd/commands/extracts/delete_extracts_command.py
tabcmd/commands/extracts/encrypt_extracts_command.py
tabcmd/commands/extracts/extracts.py
tabcmd/commands/extracts/reencrypt_extracts_command.py
tabcmd/commands/extracts/refresh_extracts_command.py
tabcmd/commands/group/__init__.py
tabcmd/commands/group/create_group_command.py
tabcmd/commands/group/delete_group_command.py
tabcmd/commands/project/__init__.py
tabcmd/commands/project/create_project_command.py
tabcmd/commands/project/delete_project_command.py
tabcmd/commands/project/publish_samples_command.py
tabcmd/commands/site/__init__.py
tabcmd/commands/site/create_site_command.py
tabcmd/commands/site/delete_site_command.py
tabcmd/commands/site/edit_site_command.py
tabcmd/commands/site/list_command.py
tabcmd/commands/site/list_sites_command.py
tabcmd/commands/user/__init__.py
tabcmd/commands/user/add_users_command.py
tabcmd/commands/user/create_site_users.py
tabcmd/commands/user/create_users_command.py
tabcmd-2.0.18.dist-info/licenses/LICENSE
tabcmd-2.0.18.dist-info/METADATA
tabcmd-2.0.18.dist-info/WHEEL
tabcmd-2.0.18.dist-info/entry_points.txt
tabcmd-2.0.18.dist-info/top_level.txt
tabcmd-2.0.18.dist-info/RECORD
