Metadata-Version: 2.4
Name: tabcmd
Version: 2.0.18
Summary: A command line client for working with Tableau Server.
Author-email: Tableau <github@tableau.com>
License: The MIT License (MIT)
Project-URL: repository, https://github.com/tableau/tabcmd
Classifier: Programming Language :: Python
Classifier: Programming Language :: Python :: 3
Classifier: Programming Language :: Python :: 3.9
Classifier: Programming Language :: Python :: 3.10
Classifier: Programming Language :: Python :: 3.11
Classifier: Programming Language :: Python :: 3.12
Classifier: Programming Language :: Python :: 3.13
Requires-Python: >=3.9
License-File: LICENSE
Requires-Dist: appdirs
Requires-Dist: doit
Requires-Dist: ftfy
Requires-Dist: pyinstaller_versionfile
Requires-Dist: pytest-order
Requires-Dist: requests<3.0,>=2.25
Requires-Dist: setuptools_scm
Requires-Dist: types-appdirs
Requires-Dist: types-mock
Requires-Dist: types-requests
Requires-Dist: types-setuptools
Requires-Dist: tableauserverclient==0.37
Requires-Dist: urllib3
Provides-Extra: test
Requires-Dist: black<23,>=22; extra == "test"
Requires-Dist: mock; extra == "test"
Requires-Dist: mypy; extra == "test"
Requires-Dist: pytest>=7.0; extra == "test"
Requires-Dist: pytest-cov; extra == "test"
Requires-Dist: pytest-order; extra == "test"
Requires-Dist: pytest-runner; extra == "test"
Requires-Dist: requests-mock<2.0,>=1.0; extra == "test"
Provides-Extra: localize
Requires-Dist: doit; extra == "localize"
Requires-Dist: ftfy; extra == "localize"
Provides-Extra: package
Requires-Dist: pyinstaller==5.13; extra == "package"
Requires-Dist: doit; extra == "package"
Dynamic: license-file
